{
  "parent": "minecraft:recipes/root",
  "criteria": {
    "has_the_recipe": {
      "conditions": {
        "recipe": "fantasy_metals:tsavorite_block"
      },
      "trigger": "minecraft:recipe_unlocked"
    },
    "has_tsavorite": {
      "conditions": {
        "items": [
          {
            "items": [
              "fantasy_metals:tsavorite"
            ]
          }
        ]
      },
      "trigger": "minecraft:inventory_changed"
    }
  },
  "requirements": [
    [
      "has_tsavorite",
      "has_the_recipe"
    ]
  ],
  "rewards": {
    "recipes": [
      "fantasy_metals:tsavorite_block"
    ]
  },
  "sends_telemetry_event": false
}