{
  "parent": "minecraft:recipes/root",
  "criteria": {
    "has_adamant_boots": {
      "conditions": {
        "items": [
          {
            "items": "fantasy_metals:adamant_boots"
          }
        ]
      },
      "trigger": "minecraft:inventory_changed"
    },
    "has_the_recipe": {
      "conditions": {
        "recipe": "minecraft:adamant_boots_blasting"
      },
      "trigger": "minecraft:recipe_unlocked"
    }
  },
  "requirements": [
    [
      "has_the_recipe",
      "has_adamant_boots"
    ]
  ],
  "rewards": {
    "recipes": [
      "minecraft:adamant_boots_blasting"
    ]
  }
}